trk_to_annotation/__init__.py
trk_to_annotation/__main__.py
trk_to_annotation/datatypes.py
trk_to_annotation/http_server.py
trk_to_annotation/id_sharding.py
trk_to_annotation/preprocessing.py
trk_to_annotation/segmentation.py
trk_to_annotation/tract_sharding.py
trk_to_annotation/utils.py
trk_to_annotation-0.0.1.dist-info/licenses/LICENSE
trk_to_annotation-0.0.1.dist-info/METADATA
trk_to_annotation-0.0.1.dist-info/WHEEL
trk_to_annotation-0.0.1.dist-info/top_level.txt
trk_to_annotation-0.0.1.dist-info/RECORD
