Metadata-Version: 2.4
Name: trk_to_annotation
Version: 0.0.1
Summary: Utilities for converting .trk tractography files into Neuroglancer precomputed annotation format, and serving them locally with HTTP requests.
Author-email: James Scherick <james_scherick@outlook.com>
License-Expression: Apache-2.0
Classifier: Programming Language :: Python :: 3
Classifier: Operating System :: OS Independent
Requires-Python: >=3.8
License-File: LICENSE
Requires-Dist: numpy>=2.3.5
Requires-Dist: nibabel>=5.3.2
Requires-Dist: cloud-volume>=12.8.0
Requires-Dist: rangehttpserver>=1.4.0
Dynamic: license-file
